cli_mit_wuff_und_wau_sandra_gufler/__init__.py
cli_mit_wuff_und_wau_sandra_gufler/create_helper_functions.py
cli_mit_wuff_und_wau_sandra_gufler/create_random_dog.py
cli_mit_wuff_und_wau_sandra_gufler/custom_types.py
cli_mit_wuff_und_wau_sandra_gufler/display_dog_data_as_table.py
cli_mit_wuff_und_wau_sandra_gufler/display_helper_functions.py
cli_mit_wuff_und_wau_sandra_gufler/fetch_and_listify_csv_dog_data.py
cli_mit_wuff_und_wau_sandra_gufler/find_dog_by.py
cli_mit_wuff_und_wau_sandra_gufler/find_helper_functions.py
cli_mit_wuff_und_wau_sandra_gufler/get_dog_statistics.py
cli_mit_wuff_und_wau_sandra_gufler/statistics_helper_functions.py
cli_mit_wuff_und_wau_sandra_gufler/wuff.py
cli_mit_wuff_und_wau_sandra_gufler-0.1.1.dist-info/METADATA
cli_mit_wuff_und_wau_sandra_gufler-0.1.1.dist-info/WHEEL
cli_mit_wuff_und_wau_sandra_gufler-0.1.1.dist-info/entry_points.txt
cli_mit_wuff_und_wau_sandra_gufler-0.1.1.dist-info/top_level.txt
cli_mit_wuff_und_wau_sandra_gufler-0.1.1.dist-info/RECORD
