Metadata-Version: 2.1
Name: cli_mit_wuff_und_wau_sandra_gufler
Version: 0.1.1
Summary: A CLI tool and library for Zürich's dog registry analysis and management
Author-email: Sandra <non.of@you.business>
License: MIT
Keywords: CLI,dog registry,statistics,random generation
Classifier: Development Status :: 4 - Beta
Classifier: Intended Audience :: Developers
Classifier: License :: OSI Approved :: MIT License
Classifier: Programming Language :: Python :: 3
Classifier: Programming Language :: Python :: 3.12
Classifier: Topic :: Utilities
Requires-Python: >=3.12
Requires-Dist: build>=1.2.2.post1
Requires-Dist: click>=8.1.7
Requires-Dist: mypy>=1.13.0
Requires-Dist: pillow>=11.0.0
Requires-Dist: python-dotenv>=1.0.1
Requires-Dist: requests>=2.32.3
Requires-Dist: rich>=13.9.4
Requires-Dist: ruff>=0.8.1
Requires-Dist: setuptools>=75.6.0
Requires-Dist: twine>=6.0.1
Requires-Dist: types-requests>=2.32.0.20241016
Requires-Dist: wheel>=0.45.1
